fpga_dds_fm_project/i2s.v
// `timescale 1us / 100ns

`define CH_WIDTH 16


module i2s (
    input wire i2s_ck,
    input wire i2s_ws,
    input wire i2s_sd,
    output reg signed [`CH_WIDTH-1:0] first_channel = 0,
    output reg signed [`CH_WIDTH-1:0] second_channel = 0,
    output reg data_updated = 1'b0 
);



reg last_ws = 1'b1;

reg [5:0] bit_num = 0; // 32 bits for whole frame
reg [`CH_WIDTH*2-1:0] frame = 0;

always @(posedge i2s_ck) begin
    if(i2s_ws == 1 && last_ws == 0) begin
        first_channel <= frame[`CH_WIDTH*2-1:`CH_WIDTH];
        second_channel <= frame[`CH_WIDTH-1:0];
        data_updated <= 1'b1;
        bit_num <= 30; // in next cycle we will read second bit, in PHILIPS mode it would be 0
        frame[31] <= i2s_sd;

    end else begin
        bit_num <= bit_num - 1;
        data_updated <= 1'b0;
        frame[bit_num] <= i2s_sd;

    end

    last_ws <= i2s_ws;
end
    



endmodule

fpga_dds_fm_project/i2s_tb.v
`timescale 1ns / 1ps

`define CH_WIDTH 32

module tb_i2s;

    // --- Sygnały ---
    reg i2s_ck;
    reg i2s_ws;
    reg i2s_sd;
    
    wire [`CH_WIDTH-1:0] first_channel;
    wire [`CH_WIDTH-1:0] second_channel;
    wire data_updated;

    // --- Instancja DUT ---
    i2s dut (
        .i2s_ck(i2s_ck),
        .i2s_ws(i2s_ws),
        .i2s_sd(i2s_sd),
        .first_channel(first_channel),
        .second_channel(second_channel),
        .data_updated(data_updated)
    );

    // --- Zegar 10MHz ---
    initial begin
        i2s_ck = 0;
        forever #50 i2s_ck = ~i2s_ck;
    end
    
    initial begin
        $dumpfile("i2s_wave.vcd");
        $dumpvars(0, tb_i2s);
    end

    // --- Task wysyłający MSB First (STM32 style) ---
    task send_frame(input [31:0] left_data, input [31:0] right_data);
        integer i;
        begin
            // 1. Kanał LEWY (WS=1). Wysyłamy bity od 31 do 0.
            i2s_ws = 1; 
            for (i = 31; i >= 0; i = i - 1) begin
                i2s_sd = left_data[i];
                @(negedge i2s_ck); 
            end

            // 2. Kanał PRAWY (WS=0). Wysyłamy bity od 31 do 0.
            i2s_ws = 0;
            for (i = 31; i >= 0; i = i - 1) begin
                i2s_sd = right_data[i];
                @(negedge i2s_ck);
            end
        end
    endtask

    // --- Monitor ---
    always @(posedge data_updated) begin
        $display("[TIME %0t ns] Ramka: Lewy=0x%h | Prawy=0x%h", 
                 $time, first_channel, second_channel);
    end

    // --- Scenariusz ---
    integer k;
    initial begin
        // Inicjalizacja na zero (bez X)
        i2s_ws = 0; i2s_sd = 0;
        #200;

        $display("=== START SYMULACJI ===");

        // Test 1: Sprawdzenie poprawności bitów (5=0101, A=1010)
        for (k = 0; k < 4; k = k + 1) begin
            send_frame(32'h55555555, 32'hAAAAAAAA);
        end

        // Test 2: Różne wartości
        send_frame(32'hDEADBEEF, 32'hCAFEBABE);
        
        // Test 3: Ciągłość
        send_frame(32'hF0F0F0F0, 32'h0F0F0F0F);

        // Zakończenie: wymuszenie ostatniego zatrzasku (WS -> 1)
        i2s_ws = 1; 
        i2s_sd = 0;
        #2000;
        
        $display("=== KONIEC ===");
        $finish;
    end

endmodule

fpga_dds_fm_project/i2s_wave.vcd
$date
	Sat Jan 31 22:50:58 2026
$end
$version
	Icarus Verilog
$end
$timescale
	1ps
$end
$scope module tb_i2s $end
$var wire 32 ! second_channel [31:0] $end
$var wire 32 " first_channel [31:0] $end
$var wire 1 # data_updated $end
$var reg 1 $ i2s_ck $end
$var reg 1 % i2s_sd $end
$var reg 1 & i2s_ws $end
$var integer 32 ' k [31:0] $end
$scope module dut $end
$var wire 1 $ i2s_ck $end
$var wire 1 % i2s_sd $end
$var wire 1 & i2s_ws $end
$var reg 6 ( bit_num [5:0] $end
$var reg 1 # data_updated $end
$var reg 32 ) first_channel [31:0] $end
$var reg 64 * frame [63:0] $end
$var reg 1 + last_ws $end
$var reg 32 , second_channel [31:0] $end
$upscope $end
$scope task send_frame $end
$var reg 32 - left_data [31:0] $end
$var reg 32 . right_data [31:0] $end
$var integer 32 / i [31:0] $end
$upscope $end
$upscope $end
$enddefinitions $end
$comment Show the parameter values. $end
$dumpall
$end
#0
$dumpvars
bx /
bx .
bx -
b0 ,
1+
b0 *
b0 )
b0 (
bx '
0&
0%
0$
0#
b0 "
b0 !
$end
#50000
0+
b111111 (
1$
#100000
0$
#150000
b111110 (
1$
#200000
1%
0$
b11110 /
1&
b10101010101010101010101010101010 .
b1010101010101010101010101010101 -
b0 '
#250000
1+
b1000000000000000000000000000000000000000000000000000000000000000 *
1#
1$
#300000
0%
b11101 /
0$
#350000
0#
b111101 (
1$
#400000
1%
b11100 /
0$
#450000
b1010000000000000000000000000000000000000000000000000000000000000 *
b111100 (
1$
#500000
0%
b11011 /
0$
#550000
b111011 (
1$
#600000
1%
b11010 /
0$
#650000
b1010100000000000000000000000000000000000000000000000000000000000 *
b111010 (
1$
#700000
0%
b11001 /
0$
#750000
b111001 (
1$
#800000
1%
b11000 /
0$
#850000
b1010101000000000000000000000000000000000000000000000000000000000 *
b111000 (
1$
#900000
0%
b10111 /
0$
#950000
b110111 (
1$
#1000000
1%
b10110 /
0$
#1050000
b1010101010000000000000000000000000000000000000000000000000000000 *
b110110 (
1$
#1100000
0%
b10101 /
0$
#1150000
b110101 (
1$
#1200000
1%
b10100 /
0$
#1250000
b1010101010100000000000000000000000000000000000000000000000000000 *
b110100 (
1$
#1300000
0%
b10011 /
0$
#1350000
b110011 (
1$
#1400000
1%
b10010 /
0$
#1450000
b1010101010101000000000000000000000000000000000000000000000000000 *
b110010 (
1$
#1500000
0%
b10001 /
0$
#1550000
b110001 (
1$
#1600000
1%
b10000 /
0$
#1650000
b1010101010101010000000000000000000000000000000000000000000000000 *
b110000 (
1$
#1700000
0%
b1111 /
0$
#1750000
b101111 (
1$
#1800000
1%
b1110 /
0$
#1850000
b1010101010101010100000000000000000000000000000000000000000000000 *
b101110 (
1$
#1900000
0%
b1101 /
0$
#1950000
b101101 (
1$
#2000000
1%
b1100 /
0$
#2050000
b1010101010101010101000000000000000000000000000000000000000000000 *
b101100 (
1$
#2100000
0%
b1011 /
0$
#2150000
b101011 (
1$
#2200000
1%
b1010 /
0$
#2250000
b1010101010101010101010000000000000000000000000000000000000000000 *
b101010 (
1$
#2300000
0%
b1001 /
0$
#2350000
b101001 (
1$
#2400000
1%
b1000 /
0$
#2450000
b1010101010101010101010100000000000000000000000000000000000000000 *
b101000 (
1$
#2500000
0%
b111 /
0$
#2550000
b100111 (
1$
#2600000
1%
b110 /
0$
#2650000
b1010101010101010101010101000000000000000000000000000000000000000 *
b100110 (
1$
#2700000
0%
b101 /
0$
#2750000
b100101 (
1$
#2800000
1%
b100 /
0$
#2850000
b1010101010101010101010101010000000000000000000000000000000000000 *
b100100 (
1$
#2900000
0%
b11 /
0$
#2950000
b100011 (
1$
#3000000
1%
b10 /
0$
#3050000
b1010101010101010101010101010100000000000000000000000000000000000 *
b100010 (
1$
#3100000
0%
b1 /
0$
#3150000
b100001 (
1$
#3200000
1%
b0 /
0$
#3250000
b1010101010101010101010101010101000000000000000000000000000000000 *
b100000 (
1$
#3300000
0&
b11111 /
0$
#3350000
0+
b1010101010101010101010101010101100000000000000000000000000000000 *
b11111 (
1$
#3400000
0%
b11110 /
0$
#3450000
b11110 (
1$
#3500000
1%
b11101 /
0$
#3550000
b1010101010101010101010101010101101000000000000000000000000000000 *
b11101 (
1$
#3600000
0%
b11100 /
0$
#3650000
b11100 (
1$
#3700000
1%
b11011 /
0$
#3750000
b1010101010101010101010101010101101010000000000000000000000000000 *
b11011 (
1$
#3800000
0%
b11010 /
0$
#3850000
b11010 (
1$
#3900000
1%
b11001 /
0$
#3950000
b1010101010101010101010101010101101010100000000000000000000000000 *
b11001 (
1$
#4000000
0%
b11000 /
0$
#4050000
b11000 (
1$
#4100000
1%
b10111 /
0$
#4150000
b1010101010101010101010101010101101010101000000000000000000000000 *
b10111 (
1$
#4200000
0%
b10110 /
0$
#4250000
b10110 (
1$
#4300000
1%
b10101 /
0$
#4350000
b1010101010101010101010101010101101010101010000000000000000000000 *
b10101 (
1$
#4400000
0%
b10100 /
0$
#4450000
b10100 (
1$
#4500000
1%
b10011 /
0$
#4550000
b1010101010101010101010101010101101010101010100000000000000000000 *
b10011 (
1$
#4600000
0%
b10010 /
0$
#4650000
b10010 (
1$
#4700000
1%
b10001 /
0$
#4750000
b1010101010101010101010101010101101010101010101000000000000000000 *
b10001 (
1$
#4800000
0%
b10000 /
0$
#4850000
b10000 (
1$
#4900000
1%
b1111 /
0$
#4950000
b1010101010101010101010101010101101010101010101010000000000000000 *
b1111 (
1$
#5000000
0%
b1110 /
0$
#5050000
b1110 (
1$
#5100000
1%
b1101 /
0$
#5150000
b1010101010101010101010101010101101010101010101010100000000000000 *
b1101 (
1$
#5200000
0%
b1100 /
0$
#5250000
b1100 (
1$
#5300000
1%
b1011 /
0$
#5350000
b1010101010101010101010101010101101010101010101010101000000000000 *
b1011 (
1$
#5400000
0%
b1010 /
0$
#5450000
b1010 (
1$
#5500000
1%
b1001 /
0$
#5550000
b1010101010101010101010101010101101010101010101010101010000000000 *
b1001 (
1$
#5600000
0%
b1000 /
0$
#5650000
b1000 (
1$
#5700000
1%
b111 /
0$
#5750000
b1010101010101010101010101010101101010101010101010101010100000000 *
b111 (
1$
#5800000
0%
b110 /
0$
#5850000
b110 (
1$
#5900000
1%
b101 /
0$
#5950000
b1010101010101010101010101010101101010101010101010101010101000000 *
b101 (
1$
#6000000
0%
b100 /
0$
#6050000
b100 (
1$
#6100000
1%
b11 /
0$
#6150000
b1010101010101010101010101010101101010101010101010101010101010000 *
b11 (
1$
#6200000
0%
b10 /
0$
#6250000
b10 (
1$
#6300000
1%
b1 /
0$
#6350000
b1010101010101010101010101010101101010101010101010101010101010100 *
b1 (
1$
#6400000
0%
b0 /
0$
#6450000
b0 (
1$
#6500000
1&
b1 '
b11111 /
0$
#6550000
1+
b10101010101010101010101010101101010101010101010101010101010100 *
b111110 (
1#
b1010101010101010101010101010100 !
b1010101010101010101010101010100 ,
b10101010101010101010101010101011 "
b10101010101010101010101010101011 )
1$
#6600000
1%
b11110 /
0$
#6650000
b110101010101010101010101010101101010101010101010101010101010100 *
0#
b111101 (
1$
#6700000
0%
b11101 /
0$
#6750000
b100101010101010101010101010101101010101010101010101010101010100 *
b111100 (
1$
#6800000
1%
b11100 /
0$
#6850000
b101101010101010101010101010101101010101010101010101010101010100 *
b111011 (
1$
#6900000
0%
b11011 /
0$
#6950000
b101001010101010101010101010101101010101010101010101010101010100 *
b111010 (
1$
#7000000
1%
b11010 /
0$
#7050000
b101011010101010101010101010101101010101010101010101010101010100 *
b111001 (
1$
#7100000
0%
b11001 /
0$
#7150000
b101010010101010101010101010101101010101010101010101010101010100 *
b111000 (
1$
#7200000
1%
b11000 /
0$
#7250000
b101010110101010101010101010101101010101010101010101010101010100 *
b110111 (
1$
#7300000
0%
b10111 /
0$
#7350000
b101010100101010101010101010101101010101010101010101010101010100 *
b110110 (
1$
#7400000
1%
b10110 /
0$
#7450000
b101010101101010101010101010101101010101010101010101010101010100 *
b110101 (
1$
#7500000
0%
b10101 /
0$
#7550000
b101010101001010101010101010101101010101010101010101010101010100 *
b110100 (
1$
#7600000
1%
b10100 /
0$
#7650000
b101010101011010101010101010101101010101010101010101010101010100 *
b110011 (
1$
#7700000
0%
b10011 /
0$
#7750000
b101010101010010101010101010101101010101010101010101010101010100 *
b110010 (
1$
#7800000
1%
b10010 /
0$
#7850000
b101010101010110101010101010101101010101010101010101010101010100 *
b110001 (
1$
#7900000
0%
b10001 /
0$
#7950000
b101010101010100101010101010101101010101010101010101010101010100 *
b110000 (
1$
#8000000
1%
b10000 /
0$
#8050000
b101010101010101101010101010101101010101010101010101010101010100 *
b101111 (
1$
#8100000
0%
b1111 /
0$
#8150000
b101010101010101001010101010101101010101010101010101010101010100 *
b101110 (
1$
#8200000
1%
b1110 /
0$
#8250000
b101010101010101011010101010101101010101010101010101010101010100 *
b101101 (
1$
#8300000
0%
b1101 /
0$
#8350000
b101010101010101010010101010101101010101010101010101010101010100 *
b101100 (
1$
#8400000
1%
b1100 /
0$
#8450000
b101010101010101010110101010101101010101010101010101010101010100 *
b101011 (
1$
#8500000
0%
b1011 /
0$
#8550000
b101010101010101010100101010101101010101010101010101010101010100 *
b101010 (
1$
#8600000
1%
b1010 /
0$
#8650000
b101010101010101010101101010101101010101010101010101010101010100 *
b101001 (
1$
#8700000
0%
b1001 /
0$
#8750000
b101010101010101010101001010101101010101010101010101010101010100 *
b101000 (
1$
#8800000
1%
b1000 /
0$
#8850000
b101010101010101010101011010101101010101010101010101010101010100 *
b100111 (
1$
#8900000
0%
b111 /
0$
#8950000
b101010101010101010101010010101101010101010101010101010101010100 *
b100110 (
1$
#9000000
1%
b110 /
0$
#9050000
b101010101010101010101010110101101010101010101010101010101010100 *
b100101 (
1$
#9100000
0%
b101 /
0$
#9150000
b101010101010101010101010100101101010101010101010101010101010100 *
b100100 (
1$
#9200000
1%
b100 /
0$
#9250000
b101010101010101010101010101101101010101010101010101010101010100 *
b100011 (
1$
#9300000
0%
b11 /
0$
#9350000
b101010101010101010101010101001101010101010101010101010101010100 *
b100010 (
1$
#9400000
1%
b10 /
0$
#9450000
b101010101010101010101010101011101010101010101010101010101010100 *
b100001 (
1$
#9500000
0%
b1 /
0$
#9550000
b101010101010101010101010101010101010101010101010101010101010100 *
b100000 (
1$
#9600000
1%
b0 /
0$
#9650000
b11111 (
1$
#9700000
0&
b11111 /
0$
#9750000
0+
b101010101010101010101010101010111010101010101010101010101010100 *
b11110 (
1$
#9800000
0%
b11110 /
0$
#9850000
b101010101010101010101010101010110010101010101010101010101010100 *
b11101 (
1$
#9900000
1%
b11101 /
0$
#9950000
b101010101010101010101010101010110110101010101010101010101010100 *
b11100 (
1$
#10000000
0%
b11100 /
0$
#10050000
b101010101010101010101010101010110100101010101010101010101010100 *
b11011 (
1$
#10100000
1%
b11011 /
0$
#10150000
b101010101010101010101010101010110101101010101010101010101010100 *
b11010 (
1$
#10200000
0%
b11010 /
0$
#10250000
b101010101010101010101010101010110101001010101010101010101010100 *
b11001 (
1$
#10300000
1%
b11001 /
0$
#10350000
b101010101010101010101010101010110101011010101010101010101010100 *
b11000 (
1$
#10400000
0%
b11000 /
0$
#10450000
b101010101010101010101010101010110101010010101010101010101010100 *
b10111 (
1$
#10500000
1%
b10111 /
0$
#10550000
b101010101010101010101010101010110101010110101010101010101010100 *
b10110 (
1$
#10600000
0%
b10110 /
0$
#10650000
b101010101010101010101010101010110101010100101010101010101010100 *
b10101 (
1$
#10700000
1%
b10101 /
0$
#10750000
b101010101010101010101010101010110101010101101010101010101010100 *
b10100 (
1$
#10800000
0%
b10100 /
0$
#10850000
b101010101010101010101010101010110101010101001010101010101010100 *
b10011 (
1$
#10900000
1%
b10011 /
0$
#10950000
b101010101010101010101010101010110101010101011010101010101010100 *
b10010 (
1$
#11000000
0%
b10010 /
0$
#11050000
b101010101010101010101010101010110101010101010010101010101010100 *
b10001 (
1$
#11100000
1%
b10001 /
0$
#11150000
b101010101010101010101010101010110101010101010110101010101010100 *
b10000 (
1$
#11200000
0%
b10000 /
0$
#11250000
b101010101010101010101010101010110101010101010100101010101010100 *
b1111 (
1$
#11300000
1%
b1111 /
0$
#11350000
b101010101010101010101010101010110101010101010101101010101010100 *
b1110 (
1$
#11400000
0%
b1110 /
0$
#11450000
b101010101010101010101010101010110101010101010101001010101010100 *
b1101 (
1$
#11500000
1%
b1101 /
0$
#11550000
b101010101010101010101010101010110101010101010101011010101010100 *
b1100 (
1$
#11600000
0%
b1100 /
0$
#11650000
b101010101010101010101010101010110101010101010101010010101010100 *
b1011 (
1$
#11700000
1%
b1011 /
0$
#11750000
b101010101010101010101010101010110101010101010101010110101010100 *
b1010 (
1$
#11800000
0%
b1010 /
0$
#11850000
b101010101010101010101010101010110101010101010101010100101010100 *
b1001 (
1$
#11900000
1%
b1001 /
0$
#11950000
b101010101010101010101010101010110101010101010101010101101010100 *
b1000 (
1$
#12000000
0%
b1000 /
0$
#12050000
b101010101010101010101010101010110101010101010101010101001010100 *
b111 (
1$
#12100000
1%
b111 /
0$
#12150000
b101010101010101010101010101010110101010101010101010101011010100 *
b110 (
1$
#12200000
0%
b110 /
0$
#12250000
b101010101010101010101010101010110101010101010101010101010010100 *
b101 (
1$
#12300000
1%
b101 /
0$
#12350000
b101010101010101010101010101010110101010101010101010101010110100 *
b100 (
1$
#12400000
0%
b100 /
0$
#12450000
b101010101010101010101010101010110101010101010101010101010100100 *
b11 (
1$
#12500000
1%
b11 /
0$
#12550000
b101010101010101010101010101010110101010101010101010101010101100 *
b10 (
1$
#12600000
0%
b10 /
0$
#12650000
b101010101010101010101010101010110101010101010101010101010101000 *
b1 (
1$
#12700000
1%
b1 /
0$
#12750000
b101010101010101010101010101010110101010101010101010101010101010 *
b0 (
1$
#12800000
0%
b0 /
0$
#12850000
b111111 (
1$
#12900000
1&
b10 '
b11111 /
0$
#12950000
1+
b111110 (
1#
b10101010101010101010101010101010 !
b10101010101010101010101010101010 ,
b1010101010101010101010101010101 "
b1010101010101010101010101010101 )
1$
#13000000
1%
b11110 /
0$
#13050000
0#
b111101 (
1$
#13100000
0%
b11101 /
0$
#13150000
b111100 (
1$
#13200000
1%
b11100 /
0$
#13250000
b111011 (
1$
#13300000
0%
b11011 /
0$
#13350000
b111010 (
1$
#13400000
1%
b11010 /
0$
#13450000
b111001 (
1$
#13500000
0%
b11001 /
0$
#13550000
b111000 (
1$
#13600000
1%
b11000 /
0$
#13650000
b110111 (
1$
#13700000
0%
b10111 /
0$
#13750000
b110110 (
1$
#13800000
1%
b10110 /
0$
#13850000
b110101 (
1$
#13900000
0%
b10101 /
0$
#13950000
b110100 (
1$
#14000000
1%
b10100 /
0$
#14050000
b110011 (
1$
#14100000
0%
b10011 /
0$
#14150000
b110010 (
1$
#14200000
1%
b10010 /
0$
#14250000
b110001 (
1$
#14300000
0%
b10001 /
0$
#14350000
b110000 (
1$
#14400000
1%
b10000 /
0$
#14450000
b101111 (
1$
#14500000
0%
b1111 /
0$
#14550000
b101110 (
1$
#14600000
1%
b1110 /
0$
#14650000
b101101 (
1$
#14700000
0%
b1101 /
0$
#14750000
b101100 (
1$
#14800000
1%
b1100 /
0$
#14850000
b101011 (
1$
#14900000
0%
b1011 /
0$
#14950000
b101010 (
1$
#15000000
1%
b1010 /
0$
#15050000
b101001 (
1$
#15100000
0%
b1001 /
0$
#15150000
b101000 (
1$
#15200000
1%
b1000 /
0$
#15250000
b100111 (
1$
#15300000
0%
b111 /
0$
#15350000
b100110 (
1$
#15400000
1%
b110 /
0$
#15450000
b100101 (
1$
#15500000
0%
b101 /
0$
#15550000
b100100 (
1$
#15600000
1%
b100 /
0$
#15650000
b100011 (
1$
#15700000
0%
b11 /
0$
#15750000
b100010 (
1$
#15800000
1%
b10 /
0$
#15850000
b100001 (
1$
#15900000
0%
b1 /
0$
#15950000
b100000 (
1$
#16000000
1%
b0 /
0$
#16050000
b11111 (
1$
#16100000
0&
b11111 /
0$
#16150000
0+
b11110 (
1$
#16200000
0%
b11110 /
0$
#16250000
b11101 (
1$
#16300000
1%
b11101 /
0$
#16350000
b11100 (
1$
#16400000
0%
b11100 /
0$
#16450000
b11011 (
1$
#16500000
1%
b11011 /
0$
#16550000
b11010 (
1$
#16600000
0%
b11010 /
0$
#16650000
b11001 (
1$
#16700000
1%
b11001 /
0$
#16750000
b11000 (
1$
#16800000
0%
b11000 /
0$
#16850000
b10111 (
1$
#16900000
1%
b10111 /
0$
#16950000
b10110 (
1$
#17000000
0%
b10110 /
0$
#17050000
b10101 (
1$
#17100000
1%
b10101 /
0$
#17150000
b10100 (
1$
#17200000
0%
b10100 /
0$
#17250000
b10011 (
1$
#17300000
1%
b10011 /
0$
#17350000
b10010 (
1$
#17400000
0%
b10010 /
0$
#17450000
b10001 (
1$
#17500000
1%
b10001 /
0$
#17550000
b10000 (
1$
#17600000
0%
b10000 /
0$
#17650000
b1111 (
1$
#17700000
1%
b1111 /
0$
#17750000
b1110 (
1$
#17800000
0%
b1110 /
0$
#17850000
b1101 (
1$
#17900000
1%
b1101 /
0$
#17950000
b1100 (
1$
#18000000
0%
b1100 /
0$
#18050000
b1011 (
1$
#18100000
1%
b1011 /
0$
#18150000
b1010 (
1$
#18200000
0%
b1010 /
0$
#18250000
b1001 (
1$
#18300000
1%
b1001 /
0$
#18350000
b1000 (
1$
#18400000
0%
b1000 /
0$
#18450000
b111 (
1$
#18500000
1%
b111 /
0$
#18550000
b110 (
1$
#18600000
0%
b110 /
0$
#18650000
b101 (
1$
#18700000
1%
b101 /
0$
#18750000
b100 (
1$
#18800000
0%
b100 /
0$
#18850000
b11 (
1$
#18900000
1%
b11 /
0$
#18950000
b10 (
1$
#19000000
0%
b10 /
0$
#19050000
b1 (
1$
#19100000
1%
b1 /
0$
#19150000
b0 (
1$
#19200000
0%
b0 /
0$
#19250000
b111111 (
1$
#19300000
1&
b11 '
b11111 /
0$
#19350000
1+
b111110 (
1#
1$
#19400000
1%
b11110 /
0$
#19450000
0#
b111101 (
1$
#19500000
0%
b11101 /
0$
#19550000
b111100 (
1$
#19600000
1%
b11100 /
0$
#19650000
b111011 (
1$
#19700000
0%
b11011 /
0$
#19750000
b111010 (
1$
#19800000
1%
b11010 /
0$
#19850000
b111001 (
1$
#19900000
0%
b11001 /
0$
#19950000
b111000 (
1$
#20000000
1%
b11000 /
0$
#20050000
b110111 (
1$
#20100000
0%
b10111 /
0$
#20150000
b110110 (
1$
#20200000
1%
b10110 /
0$
#20250000
b110101 (
1$
#20300000
0%
b10101 /
0$
#20350000
b110100 (
1$
#20400000
1%
b10100 /
0$
#20450000
b110011 (
1$
#20500000
0%
b10011 /
0$
#20550000
b110010 (
1$
#20600000
1%
b10010 /
0$
#20650000
b110001 (
1$
#20700000
0%
b10001 /
0$
#20750000
b110000 (
1$
#20800000
1%
b10000 /
0$
#20850000
b101111 (
1$
#20900000
0%
b1111 /
0$
#20950000
b101110 (
1$
#21000000
1%
b1110 /
0$
#21050000
b101101 (
1$
#21100000
0%
b1101 /
0$
#21150000
b101100 (
1$
#21200000
1%
b1100 /
0$
#21250000
b101011 (
1$
#21300000
0%
b1011 /
0$
#21350000
b101010 (
1$
#21400000
1%
b1010 /
0$
#21450000
b101001 (
1$
#21500000
0%
b1001 /
0$
#21550000
b101000 (
1$
#21600000
1%
b1000 /
0$
#21650000
b100111 (
1$
#21700000
0%
b111 /
0$
#21750000
b100110 (
1$
#21800000
1%
b110 /
0$
#21850000
b100101 (
1$
#21900000
0%
b101 /
0$
#21950000
b100100 (
1$
#22000000
1%
b100 /
0$
#22050000
b100011 (
1$
#22100000
0%
b11 /
0$
#22150000
b100010 (
1$
#22200000
1%
b10 /
0$
#22250000
b100001 (
1$
#22300000
0%
b1 /
0$
#22350000
b100000 (
1$
#22400000
1%
b0 /
0$
#22450000
b11111 (
1$
#22500000
0&
b11111 /
0$
#22550000
0+
b11110 (
1$
#22600000
0%
b11110 /
0$
#22650000
b11101 (
1$
#22700000
1%
b11101 /
0$
#22750000
b11100 (
1$
#22800000
0%
b11100 /
0$
#22850000
b11011 (
1$
#22900000
1%
b11011 /
0$
#22950000
b11010 (
1$
#23000000
0%
b11010 /
0$
#23050000
b11001 (
1$
#23100000
1%
b11001 /
0$
#23150000
b11000 (
1$
#23200000
0%
b11000 /
0$
#23250000
b10111 (
1$
#23300000
1%
b10111 /
0$
#23350000
b10110 (
1$
#23400000
0%
b10110 /
0$
#23450000
b10101 (
1$
#23500000
1%
b10101 /
0$
#23550000
b10100 (
1$
#23600000
0%
b10100 /
0$
#23650000
b10011 (
1$
#23700000
1%
b10011 /
0$
#23750000
b10010 (
1$
#23800000
0%
b10010 /
0$
#23850000
b10001 (
1$
#23900000
1%
b10001 /
0$
#23950000
b10000 (
1$
#24000000
0%
b10000 /
0$
#24050000
b1111 (
1$
#24100000
1%
b1111 /
0$
#24150000
b1110 (
1$
#24200000
0%
b1110 /
0$
#24250000
b1101 (
1$
#24300000
1%
b1101 /
0$
#24350000
b1100 (
1$
#24400000
0%
b1100 /
0$
#24450000
b1011 (
1$
#24500000
1%
b1011 /
0$
#24550000
b1010 (
1$
#24600000
0%
b1010 /
0$
#24650000
b1001 (
1$
#24700000
1%
b1001 /
0$
#24750000
b1000 (
1$
#24800000
0%
b1000 /
0$
#24850000
b111 (
1$
#24900000
1%
b111 /
0$
#24950000
b110 (
1$
#25000000
0%
b110 /
0$
#25050000
b101 (
1$
#25100000
1%
b101 /
0$
#25150000
b100 (
1$
#25200000
0%
b100 /
0$
#25250000
b11 (
1$
#25300000
1%
b11 /
0$
#25350000
b10 (
1$
#25400000
0%
b10 /
0$
#25450000
b1 (
1$
#25500000
1%
b1 /
0$
#25550000
b0 (
1$
#25600000
0%
b0 /
0$
#25650000
b111111 (
1$
#25700000
1%
1&
b11001010111111101011101010111110 .
b11011110101011011011111011101111 -
b100 '
b11111 /
0$
#25750000
1+
b1101010101010101010101010101010110101010101010101010101010101010 *
b111110 (
1#
1$
#25800000
b11110 /
0$
#25850000
0#
b111101 (
1$
#25900000
0%
b11101 /
0$
#25950000
b111100 (
1$
#26000000
1%
b11100 /
0$
#26050000
b111011 (
1$
#26100000
b11011 /
0$
#26150000
b1101110101010101010101010101010110101010101010101010101010101010 *
b111010 (
1$
#26200000
b11010 /
0$
#26250000
b111001 (
1$
#26300000
b11001 /
0$
#26350000
b1101111101010101010101010101010110101010101010101010101010101010 *
b111000 (
1$
#26400000
0%
b11000 /
0$
#26450000
b1101111001010101010101010101010110101010101010101010101010101010 *
b110111 (
1$
#26500000
1%
b10111 /
0$
#26550000
b1101111011010101010101010101010110101010101010101010101010101010 *
b110110 (
1$
#26600000
0%
b10110 /
0$
#26650000
b1101111010010101010101010101010110101010101010101010101010101010 *
b110101 (
1$
#26700000
1%
b10101 /
0$
#26750000
b1101111010110101010101010101010110101010101010101010101010101010 *
b110100 (
1$
#26800000
0%
b10100 /
0$
#26850000
b1101111010100101010101010101010110101010101010101010101010101010 *
b110011 (
1$
#26900000
1%
b10011 /
0$
#26950000
b1101111010101101010101010101010110101010101010101010101010101010 *
b110010 (
1$
#27000000
b10010 /
0$
#27050000
b110001 (
1$
#27100000
0%
b10001 /
0$
#27150000
b110000 (
1$
#27200000
1%
b10000 /
0$
#27250000
b101111 (
1$
#27300000
b1111 /
0$
#27350000
b1101111010101101110101010101010110101010101010101010101010101010 *
b101110 (
1$
#27400000
0%
b1110 /
0$
#27450000
b1101111010101101100101010101010110101010101010101010101010101010 *
b101101 (
1$
#27500000
1%
b1101 /
0$
#27550000
b1101111010101101101101010101010110101010101010101010101010101010 *
b101100 (
1$
#27600000
b1100 /
0$
#27650000
b101011 (
1$
#27700000
b1011 /
0$
#27750000
b1101111010101101101111010101010110101010101010101010101010101010 *
b101010 (
1$
#27800000
b1010 /
0$
#27850000
b101001 (
1$
#27900000
b1001 /
0$
#27950000
b1101111010101101101111110101010110101010101010101010101010101010 *
b101000 (
1$
#28000000
0%
b1000 /
0$
#28050000
b1101111010101101101111100101010110101010101010101010101010101010 *
b100111 (
1$
#28100000
1%
b111 /
0$
#28150000
b1101111010101101101111101101010110101010101010101010101010101010 *
b100110 (
1$
#28200000
b110 /
0$
#28250000
b100101 (
1$
#28300000
b101 /
0$
#28350000
b1101111010101101101111101111010110101010101010101010101010101010 *
b100100 (
1$
#28400000
0%
b100 /
0$
#28450000
b1101111010101101101111101110010110101010101010101010101010101010 *
b100011 (
1$
#28500000
1%
b11 /
0$
#28550000
b1101111010101101101111101110110110101010101010101010101010101010 *
b100010 (
1$
#28600000
b10 /
0$
#28650000
b100001 (
1$
#28700000
b1 /
0$
#28750000
b1101111010101101101111101110111110101010101010101010101010101010 *
b100000 (
1$
#28800000
b0 /
0$
#28850000
b11111 (
1$
#28900000
0&
b11111 /
0$
#28950000
0+
b11110 (
1$
#29000000
b11110 /
0$
#29050000
b1101111010101101101111101110111111101010101010101010101010101010 *
b11101 (
1$
#29100000
0%
b11101 /
0$
#29150000
b1101111010101101101111101110111111001010101010101010101010101010 *
b11100 (
1$
#29200000
b11100 /
0$
#29250000
b11011 (
1$
#29300000
1%
b11011 /
0$
#29350000
b11010 (
1$
#29400000
0%
b11010 /
0$
#29450000
b11001 (
1$
#29500000
1%
b11001 /
0$
#29550000
b11000 (
1$
#29600000
0%
b11000 /
0$
#29650000
b10111 (
1$
#29700000
1%
b10111 /
0$
#29750000
b10110 (
1$
#29800000
b10110 /
0$
#29850000
b1101111010101101101111101110111111001010111010101010101010101010 *
b10101 (
1$
#29900000
b10101 /
0$
#29950000
b10100 (
1$
#30000000
b10100 /
0$
#30050000
b1101111010101101101111101110111111001010111110101010101010101010 *
b10011 (
1$
#30100000
b10011 /
0$
#30150000
b10010 (
1$
#30200000
b10010 /
0$
#30250000
b1101111010101101101111101110111111001010111111101010101010101010 *
b10001 (
1$
#30300000
b10001 /
0$
#30350000
b10000 (
1$
#30400000
0%
b10000 /
0$
#30450000
b1111 (
1$
#30500000
1%
b1111 /
0$
#30550000
b1110 (
1$
#30600000
0%
b1110 /
0$
#30650000
b1101 (
1$
#30700000
1%
b1101 /
0$
#30750000
b1100 (
1$
#30800000
b1100 /
0$
#30850000
b1101111010101101101111101110111111001010111111101011101010101010 *
b1011 (
1$
#30900000
b1011 /
0$
#30950000
b1010 (
1$
#31000000
0%
b1010 /
0$
#31050000
b1001 (
1$
#31100000
1%
b1001 /
0$
#31150000
b1000 (
1$
#31200000
0%
b1000 /
0$
#31250000
b111 (
1$
